ladybug_display/__init__.py
ladybug_display/_base.py
ladybug_display/_extend_ladybug.py
ladybug_display/altnumber.py
ladybug_display/analysis.py
ladybug_display/context.py
ladybug_display/dictutil.py
ladybug_display/typing.py
ladybug_display/visualization.py
ladybug_display/extension/__init__.py
ladybug_display/extension/adaptivechart.py
ladybug_display/extension/compass.py
ladybug_display/extension/hourlyplot.py
ladybug_display/extension/monthlychart.py
ladybug_display/extension/psychchart.py
ladybug_display/extension/raddome.py
ladybug_display/extension/radrose.py
ladybug_display/extension/skydome.py
ladybug_display/extension/sunpath.py
ladybug_display/extension/viewsphere.py
ladybug_display/extension/windprofile.py
ladybug_display/extension/windrose.py
ladybug_display/extension/study/__init__.py
ladybug_display/extension/study/directsun.py
ladybug_display/extension/study/radiation.py
ladybug_display/geometry2d/__init__.py
ladybug_display/geometry2d/_base.py
ladybug_display/geometry2d/arc.py
ladybug_display/geometry2d/line.py
ladybug_display/geometry2d/mesh.py
ladybug_display/geometry2d/point.py
ladybug_display/geometry2d/polygon.py
ladybug_display/geometry2d/polyline.py
ladybug_display/geometry2d/ray.py
ladybug_display/geometry2d/vector.py
ladybug_display/geometry3d/__init__.py
ladybug_display/geometry3d/_base.py
ladybug_display/geometry3d/arc.py
ladybug_display/geometry3d/cone.py
ladybug_display/geometry3d/cylinder.py
ladybug_display/geometry3d/face.py
ladybug_display/geometry3d/line.py
ladybug_display/geometry3d/mesh.py
ladybug_display/geometry3d/plane.py
ladybug_display/geometry3d/point.py
ladybug_display/geometry3d/polyface.py
ladybug_display/geometry3d/polyline.py
ladybug_display/geometry3d/ray.py
ladybug_display/geometry3d/sphere.py
ladybug_display/geometry3d/text.py
ladybug_display/geometry3d/vector.py
ladybug_display/svg/__init__.py
ladybug_display/svg/_mixins.py
ladybug_display/svg/_path.py
ladybug_display/svg/_transforms.py
ladybug_display-0.13.3.dist-info/licenses/LICENSE
ladybug_display-0.13.3.dist-info/METADATA
ladybug_display-0.13.3.dist-info/WHEEL
ladybug_display-0.13.3.dist-info/top_level.txt
ladybug_display-0.13.3.dist-info/RECORD
